TracNginxCacheSupport-1.0.dist-info/DESCRIPTION.rst
TracNginxCacheSupport-1.0.dist-info/METADATA
TracNginxCacheSupport-1.0.dist-info/RECORD
TracNginxCacheSupport-1.0.dist-info/WHEEL
TracNginxCacheSupport-1.0.dist-info/entry_points.txt
TracNginxCacheSupport-1.0.dist-info/metadata.json
TracNginxCacheSupport-1.0.dist-info/top_level.txt
nginxcachesupport/__init__.py
