Metadata-Version: 2.0
Name: TracNginxCacheSupport
Version: 1.0
Summary: Add support for Nginx caching to Trac
Home-page: https://github.com/trac-hacks/TracNginxCacheSupport
Author: Colin Snover
Author-email: tracplugins@zetafleet.com
License: 3-Clause BSD
Keywords: trac plugin nginx cache
Platform: UNKNOWN
Classifier: Framework :: Trac
Requires-Dist: Trac
